decouple_aws/__init__.py
decouple_aws/exceptions.py
decouple_aws/repository.py
python_decouple_aws-0.3.2.dist-info/LICENSE
python_decouple_aws-0.3.2.dist-info/WHEEL
python_decouple_aws-0.3.2.dist-info/METADATA
python_decouple_aws-0.3.2.dist-info/RECORD
