Metadata-Version: 2.1
Name: python-decouple-aws
Version: 0.3.2
Summary: AWS Extensions for Python Decouple
Home-page: https://github.com/AzMoo/python-decouple-aws
License: MIT
Author: Matt Magin
Author-email: matt.magin@cmv.com.au
Requires-Python: >=3.4,<4.0
Classifier: License :: OSI Approved :: MIT License
Classifier: Programming Language :: Python :: 3
Classifier: Programming Language :: Python :: 3.4
Classifier: Programming Language :: Python :: 3.5
Classifier: Programming Language :: Python :: 3.6
Classifier: Programming Language :: Python :: 3.7
Requires-Dist: boto3 (>=1.7,<2.0)
Requires-Dist: python-decouple (>=3.1,<4.0)
Project-URL: Repository, https://github.com/AzMoo/python-decouple-aws
